<Properties StartupConfiguration="{3EBAE605-9FB6-4023-8DF9-BCADB07F9B59}|Default">
  <MonoDevelop.Ide.Workbench ActiveDocument="YoutubePlayer/SecondViewController.cs">
    <Files>
      <File FileName="YoutubePlayer/Main.storyboard" />
      <File FileName="YoutubePlayer/FirstViewController.cs" Line="26" Column="110" />
      <File FileName="YoutubePlayer/Main.cs" Line="13" Column="10" />
      <File FileName="YoutubePlayer/SecondViewController.cs" Line="5" Column="3" />
    </Files>
    <Pads>
      <Pad Id="ProjectPad">
        <State name="__root__">
          <Node name="YoutubePlayer" expanded="True">
            <Node name="YoutubePlayer" expanded="True">
              <Node name="Resources" expanded="True" />
              <Node name="SecondViewController.cs" selected="True" />
            </Node>
          </Node>
        </State>
      </Pad>
    </Pads>
  </MonoDevelop.Ide.Workbench>
  <MonoDevelop.Ide.ItemProperties.YoutubePlayer PreferredExecutionTarget="MonoDevelop.IPhone.IPhoneSimulatorTarget.537E1CDE-4F8A-4224-A57D-2877F450216B" />
  <MonoDevelop.Ide.DebuggingService.PinnedWatches />
  <MonoDevelop.Ide.Workspace ActiveConfiguration="Debug|iPhoneSimulator" />
  <MonoDevelop.Ide.DebuggingService.Breakpoints>
    <BreakpointStore />
  </MonoDevelop.Ide.DebuggingService.Breakpoints>
  <MultiItemStartupConfigurations />
</Properties>